{
"type": "FeatureCollection",
"name": "airspace_levels",
"crs": { "type": "name", "properties": { "name": "urn:ogc:def:crs:OGC:1.3:CRS84" } },
"features": [
{ "type": "Feature", "properties": { "name": "15" }, "geometry": { "type": "Point", "coordinates": [ 8.46457, 49.900684722222223 ] } },
{ "type": "Feature", "properties": { "name": "35" }, "geometry": { "type": "Point", "coordinates": [ 8.964568333333332, 49.907411666666668 ] } },
{ "type": "Feature", "properties": { "name": "45#1" }, "geometry": { "type": "Point", "coordinates": [ 8.248639722222221, 49.7043425 ] } },
{ "type": "Feature", "properties": { "name": "45#2" }, "geometry": { "type": "Point", "coordinates": [ 8.515298924226929, 50.238707052769435 ] } },
{ "type": "Feature", "properties": { "name": "55#1" }, "geometry": { "type": "Point", "coordinates": [ 9.357388888888888, 49.955852777777778 ] } },
{ "type": "Feature", "properties": { "name": "45#3" }, "geometry": { "type": "Point", "coordinates": [ 7.775002777777778, 49.957321111111114 ] } },
{ "type": "Feature", "properties": { "name": "55#2" }, "geometry": { "type": "Point", "coordinates": [ 8.760422777777778, 50.374779722222222 ] } },
{ "type": "Feature", "properties": { "name": "65#1" }, "geometry": { "type": "Point", "coordinates": [ 7.831316388888888, 50.130595277777779 ] } },
{ "type": "Feature", "properties": { "name": "65#2" }, "geometry": { "type": "Point", "coordinates": [ 9.4963225, 50.184355 ] } },
{ "type": "Feature", "properties": { "name": "85#1" }, "geometry": { "type": "Point", "coordinates": [ 8.068280833333333, 50.316944166666673 ] } },
{ "type": "Feature", "properties": { "name": "85#2" }, "geometry": { "type": "Point", "coordinates": [ 9.331290555555555, 49.704915 ] } },
{ "type": "Feature", "properties": { "name": "85#3" }, "geometry": { "type": "Point", "coordinates": [ 9.61521389003811, 50.509015825586154 ] } },
{ "type": "Feature", "properties": { "name": "25#1" }, "geometry": { "type": "Point", "coordinates": [ 8.477993611111112, 49.818898333333337 ] } },
{ "type": "Feature", "properties": { "name": "25#2" }, "geometry": { "type": "Point", "coordinates": [ 8.910470555555555, 50.064785277777773 ] } },
{ "type": "Feature", "properties": { "name": "65#3" }, "geometry": { "type": "Point", "coordinates": [ 7.721150555555556, 49.85039861111111 ] } }
]
}
